http_api_client/__init__.py
http_api_client/core/__init__.py
http_api_client/core/responses.py
http_api_client/io/__init__.py
http_api_client/io/lpickle.py
http_api_client-0.1.0.dist-info/METADATA
http_api_client-0.1.0.dist-info/WHEEL
http_api_client-0.1.0.dist-info/top_level.txt
http_api_client-0.1.0.dist-info/RECORD
