Metadata-Version: 2.1
Name: http-api-client
Version: 0.1.0
Summary: Library for HTTP Api
Home-page: https://gitlab.bjarnessen.no/bjarne/http_api_client/
Author: Bjarne Rørnes
Author-email: bjarne@bjarnessen.no
License: UNKNOWN
Project-URL: Bug Reports, https://gitlab.bjarnessen.no/bjarne/http_api_client/issues
Project-URL: Tracker, https://gitlab.bjarnessen.no/bjarne/http_api_client/issues
Project-URL: Source, https://gitlab.bjarnessen.no/bjarne/http_api_client/
Keywords: python development library
Platform: UNKNOWN
Classifier: Development Status :: 4 - Beta
Classifier: Intended Audience :: Developers
Classifier: Topic :: Software Development :: Libraries
Classifier: License :: OSI Approved :: MIT License
Classifier: Programming Language :: Python :: 3
Requires-Python: >=3.6
Requires-Dist: requests
